geomloss/__init__.py
geomloss/kernel_samples.py
geomloss/samples_loss.py
geomloss/sinkhorn_divergence.py
geomloss/sinkhorn_samples.py
geomloss/utils.py
geomloss-0.2.4.dist-info/LICENSE.txt
geomloss-0.2.4.dist-info/METADATA
geomloss-0.2.4.dist-info/WHEEL
geomloss-0.2.4.dist-info/top_level.txt
geomloss-0.2.4.dist-info/RECORD
