Metadata-Version: 2.1
Name: geomloss
Version: 0.2.4
Summary: Geometric loss functions between point clouds, images and volumes.
Home-page: UNKNOWN
Author: Jean Feydy
Author-email: jfeydy@ic.ac.uk
License: LICENSE.txt
Keywords: kernels optimal transport measure loss geometry
Platform: UNKNOWN
Classifier: Development Status :: 2 - Pre-Alpha
Classifier: Intended Audience :: Developers
Classifier: Topic :: Scientific/Engineering
Classifier: License :: OSI Approved :: MIT License
Classifier: Operating System :: POSIX :: Linux
Classifier: Operating System :: MacOS :: MacOS X
Classifier: Operating System :: Microsoft :: Windows
Classifier: Programming Language :: Python :: 3 :: Only
Requires-Python: >=3
Requires-Dist: numpy
Provides-Extra: full
Requires-Dist: pykeops[full] ; extra == 'full'
Requires-Dist: cmake (>=3.18) ; extra == 'full'
